PyObjCTools/KeyValueCoding.py
PyObjCTools/MachSignals.py
PyObjCTools/Signals.py
PyObjCTools/TestSupport.py
objc/__init__.py
objc/_bridges.py
objc/_bridgesupport.py
objc/_callable_docstr.py
objc/_category.py
objc/_compat.py
objc/_context.py
objc/_convenience.py
objc/_convenience_mapping.py
objc/_convenience_nsarray.py
objc/_convenience_nsdata.py
objc/_convenience_nsdecimal.py
objc/_convenience_nsdictionary.py
objc/_convenience_nsobject.py
objc/_convenience_nsset.py
objc/_convenience_nsstring.py
objc/_convenience_sequence.py
objc/_descriptors.py
objc/_dyld.py
objc/_framework.py
objc/_informal_protocol.py
objc/_lazyimport.py
objc/_locking.py
objc/_machsignals.cpython-312-darwin.so
objc/_new.py
objc/_objc.cpython-312-darwin.so
objc/_properties.py
objc/_protocols.py
objc/_pycoder.py
objc/_pythonify.py
objc/_structtype.py
objc/_transform.py
objc/_types.py
objc/simd.py
pyobjc_core-12.1.dist-info/include/pyobjc-api.h
pyobjc_core-12.1.dist-info/include/pyobjc-compat.h
pyobjc_core-12.1.dist-info/METADATA
pyobjc_core-12.1.dist-info/WHEEL
pyobjc_core-12.1.dist-info/pyobjc-build-info.txt
pyobjc_core-12.1.dist-info/top_level.txt
pyobjc_core-12.1.dist-info/RECORD
